[
  {
    "Title": "Brave New World",
    "Author": "Aldous Huxley",
    "Price": 500.0
  },
  {
    "Title": "1984",
    "Author": "Бартек",
    "Price": 0.0
  },
  {
    "Title": "The Myth of Normal",
    "Author": "Gabor Mate",
    "Price": 600.0
  },
  {
    "Title": "Elly Griffith",
    "Author": "The Crossing Places",
    "Price": 400.0
  },
  {
    "Title": "Elly Griffith",
    "Author": "The Chalk Pit",
    "Price": 240.0
  },
  {
    "Title": "Elly Griffith",
    "Author": "The Ghost Fields",
    "Price": 250.0
  },
  {
    "Title": "Play with fire",
    "Author": "T.M. Payne",
    "Price": 150.0
  },
  {
    "Title": "Long time dead",
    "Author": "T.M. Payne",
    "Price": 200.0
  },
  {
    "Title": "This ends now",
    "Author": "T.M. Payne",
    "Price": 300.0
  },
  {
    "Title": "Шантарам",
    "Author": "Грегорі Девід Робертс",
    "Price": 2000.0
  },
  {
    "Title": "Тінь Гори",
    "Author": "Грегорі Девід Робертс",
    "Price": 1500.0
  }
]